{
  "temperature": 1.240065674210219,
  "top_p": 0.776030045761596,
  "top_k": 48,
  "temperature_coding": 1.1839647171153018,
  "top_p_coding": 0.995459973252883,
  "top_k_coding": 80,
  "n_repetitions": 8,
  "TOTAL_TOKENS": 1600,
  "REFLECTION": false,
  "starting_counts": [
    4,
    1
  ],
  "prompt_options": [
    "\nBelow is a math problem you are to solve (natural number answer):\n\"{}\"\nTo accomplish this, first list the problem's constraints, conditions and related knowledge, and thens solve the problem step by step. Be clear so even an idiot can follow your instructions. After solving the problem, output the final numerical answer within \\boxed{}.\n\nAssistant:",
    "\nBelow is a math problem you are to solve (natural number answer!):\n\"{}\"\nAnalyze the problem and think step by step to come to a solution with programs. After solving the problem, output the final numerical answer within \\boxed{}.\n\nAssistant:"
  ]
}