{
  "temperature": 1.279069691008346,
  "top_p": 0.7990479553752677,
  "top_k": 64,
  "temperature_coding": 0.6032742059275287,
  "top_p_coding": 0.8456414597789179,
  "top_k_coding": 48,
  "n_repetitions": 16,
  "TOTAL_TOKENS": 1600,
  "REFLECTION": false,
  "starting_counts": [
    3,
    3
  ],
  "prompt_options": [
    "\nSolve the following problem with a Python Script (positive numerical answer):\n\"{}\"\nWrite comments to indicate the steps you take. Please put your final solution into \\boxed{}.\n\nAssistant:\n\nApproach:",
    "\nSolve the following problem with a Python Script (positive numerical answer):\n\"{}\"\nWrite comments to indicate the steps you take. Please put your final solution into \\boxed{}.\n\nAssistant:\n\nApproach:"
  ]
}